CHANGES.txt
DESC.txt
MANIFEST.in
README.md
setup.py
FindFunc.egg-info/PKG-INFO
FindFunc.egg-info/SOURCES.txt
FindFunc.egg-info/dependency_links.txt
FindFunc.egg-info/entry_points.txt
FindFunc.egg-info/requires.txt
FindFunc.egg-info/top_level.txt
docs/README.txt
findfunc/__init__.py
findfunc/__main__.py
findfunc/json_settings.py
findfunc/tools.py
test/__init__.py
test/test_findfunc.py