Metadata-Version: 1.1
Name: FindFunc
Version: 0.4.4
Summary: Finds function definitions/signatures from the command line.
